tensor_toolkit-0.1.1.dist-info/licenses/LICENSE
tensorkit/__init__.py
tensorkit/tensor_checks.py
tensorkit/tensor_utils.py
tensor_toolkit-0.1.1.dist-info/METADATA
tensor_toolkit-0.1.1.dist-info/WHEEL
tensor_toolkit-0.1.1.dist-info/top_level.txt
tensor_toolkit-0.1.1.dist-info/RECORD
