Metadata-Version: 2.4
Name: tensor-toolkit
Version: 0.1.1
Summary: Essential PyTorch utilities for fast and flexible tensor operations
Author-email: Suresh K <sureshstr38@gmail.com>
License-Expression: MIT
Project-URL: Homepage, https://github.com/suressssz/tensor-toolkit
Project-URL: Bugtracker, https://github.com/suressssz/tensor-toolkit/issues
Project-URL: Repository, https://github.com/suressssz/tensor-toolkit
Requires-Python: >=3.8
License-File: LICENSE
Requires-Dist: torch>=1.10.0
Requires-Dist: numpy>=1.21.0
Dynamic: license-file
